{"sprites":[{"min":{"x":34,"y":60},"max":{"x":88,"y":124}},{"min":{"x":160,"y":61},"max":{"x":214,"y":124}},{"min":{"x":286,"y":61},"max":{"x":340,"y":124}},{"min":{"x":416,"y":61},"max":{"x":464,"y":124}},{"min":{"x":544,"y":61},"max":{"x":588,"y":124}},{"min":{"x":672,"y":56},"max":{"x":718,"y":124}},{"min":{"x":802,"y":55},"max":{"x":852,"y":124}},{"min":{"x":931,"y":44},"max":{"x":970,"y":124}},{"min":{"x":1058,"y":60},"max":{"x":1099,"y":124}},{"min":{"x":1186,"y":59},"max":{"x":1227,"y":124}},{"min":{"x":1320,"y":58},"max":{"x":1356,"y":124}},{"min":{"x":1445,"y":56},"max":{"x":1484,"y":124}},{"min":{"x":1571,"y":51},"max":{"x":1612,"y":124}},{"min":{"x":1698,"y":49},"max":{"x":1741,"y":124}},{"min":{"x":1826,"y":49},"max":{"x":1869,"y":124}},{"min":{"x":1955,"y":49},"max":{"x":1997,"y":124}},{"min":{"x":2082,"y":60},"max":{"x":2124,"y":124}},{"min":{"x":2212,"y":61},"max":{"x":2252,"y":124}},{"min":{"x":2340,"y":61},"max":{"x":2387,"y":124}},{"min":{"x":2468,"y":61},"max":{"x":2519,"y":124}},{"min":{"x":2596,"y":22},"max":{"x":2633,"y":84}},{"min":{"x":2722,"y":22},"max":{"x":2760,"y":83}},{"min":{"x":2848,"y":23},"max":{"x":2887,"y":83}},{"min":{"x":2975,"y":24},"max":{"x":3014,"y":83}},{"min":{"x":3103,"y":27},"max":{"x":3148,"y":83}},{"min":{"x":3234,"y":33},"max":{"x":3279,"y":82}},{"min":{"x":3366,"y":40},"max":{"x":3410,"y":83}},{"min":{"x":3499,"y":48},"max":{"x":3540,"y":91}},{"min":{"x":3631,"y":55},"max":{"x":3666,"y":93}},{"min":{"x":3758,"y":56},"max":{"x":3798,"y":93}},{"min":{"x":3886,"y":57},"max":{"x":3926,"y":93}},{"min":{"x":4013,"y":59},"max":{"x":4054,"y":93}},{"min":{"x":4141,"y":61},"max":{"x":4182,"y":93}},{"min":{"x":4269,"y":63},"max":{"x":4310,"y":93}},{"min":{"x":4396,"y":66},"max":{"x":4438,"y":93}},{"min":{"x":4522,"y":66},"max":{"x":4566,"y":93}},{"min":{"x":4648,"y":64},"max":{"x":4694,"y":95}},{"min":{"x":4775,"y":62},"max":{"x":4822,"y":97}},{"min":{"x":4902,"y":61},"max":{"x":4950,"y":100}},{"min":{"x":5028,"y":61},"max":{"x":5078,"y":100}},{"min":{"x":27,"y":189},"max":{"x":85,"y":255}},{"min":{"x":153,"y":189},"max":{"x":210,"y":254}},{"min":{"x":287,"y":189},"max":{"x":333,"y":254}},{"min":{"x":409,"y":188},"max":{"x":457,"y":254}},{"min":{"x":534,"y":189},"max":{"x":584,"y":254}},{"min":{"x":663,"y":184},"max":{"x":717,"y":254}},{"min":{"x":793,"y":183},"max":{"x":847,"y":254}},{"min":{"x":921,"y":175},"max":{"x":969,"y":254}},{"min":{"x":1048,"y":186},"max":{"x":1098,"y":254}},{"min":{"x":1157,"y":186},"max":{"x":1226,"y":254}},{"min":{"x":1285,"y":184},"max":{"x":1355,"y":254}},{"min":{"x":1417,"y":181},"max":{"x":1483,"y":254}},{"min":{"x":1548,"y":177},"max":{"x":1611,"y":254}},{"min":{"x":1680,"y":175},"max":{"x":1740,"y":254}},{"min":{"x":1810,"y":175},"max":{"x":1868,"y":254}},{"min":{"x":1938,"y":175},"max":{"x":1996,"y":254}},{"min":{"x":2068,"y":186},"max":{"x":2124,"y":254}},{"min":{"x":2195,"y":188},"max":{"x":2251,"y":254}},{"min":{"x":2325,"y":189},"max":{"x":2378,"y":254}},{"min":{"x":2456,"y":189},"max":{"x":2512,"y":254}},{"min":{"x":2607,"y":222},"max":{"x":2639,"y":285}},{"min":{"x":2734,"y":220},"max":{"x":2765,"y":284}},{"min":{"x":2861,"y":220},"max":{"x":2895,"y":283}},{"min":{"x":2987,"y":219},"max":{"x":3026,"y":282}},{"min":{"x":3113,"y":221},"max":{"x":3157,"y":282}},{"min":{"x":3240,"y":225},"max":{"x":3286,"y":282}},{"min":{"x":3365,"y":231},"max":{"x":3414,"y":284}},{"min":{"x":3490,"y":238},"max":{"x":3540,"y":287}},{"min":{"x":33,"y":317},"max":{"x":73,"y":382}},{"min":{"x":159,"y":317},"max":{"x":201,"y":382}},{"min":{"x":283,"y":315},"max":{"x":330,"y":382}},{"min":{"x":410,"y":317},"max":{"x":458,"y":382}},{"min":{"x":536,"y":317},"max":{"x":587,"y":381}},{"min":{"x":662,"y":316},"max":{"x":715,"y":381}},{"min":{"x":789,"y":311},"max":{"x":843,"y":381}},{"min":{"x":915,"y":304},"max":{"x":971,"y":381}},{"min":{"x":1043,"y":294},"max":{"x":1099,"y":381}},{"min":{"x":1159,"y":302},"max":{"x":1228,"y":381}},{"min":{"x":1290,"y":311},"max":{"x":1357,"y":381}},{"min":{"x":1412,"y":305},"max":{"x":1485,"y":381}},{"min":{"x":1544,"y":302},"max":{"x":1614,"y":381}},{"min":{"x":1676,"y":301},"max":{"x":1742,"y":381}},{"min":{"x":1805,"y":300},"max":{"x":1870,"y":381}},{"min":{"x":1933,"y":301},"max":{"x":1998,"y":381}},{"min":{"x":2064,"y":307},"max":{"x":2125,"y":381}},{"min":{"x":2195,"y":313},"max":{"x":2251,"y":381}},{"min":{"x":2327,"y":317},"max":{"x":2378,"y":382}},{"min":{"x":2460,"y":317},"max":{"x":2505,"y":382}},{"min":{"x":2601,"y":323},"max":{"x":2641,"y":383}},{"min":{"x":2729,"y":321},"max":{"x":2769,"y":384}},{"min":{"x":2858,"y":319},"max":{"x":2895,"y":384}},{"min":{"x":2986,"y":318},"max":{"x":3022,"y":384}},{"min":{"x":3113,"y":319},"max":{"x":3150,"y":384}},{"min":{"x":3238,"y":322},"max":{"x":3280,"y":384}},{"min":{"x":3365,"y":326},"max":{"x":3411,"y":384}},{"min":{"x":3489,"y":331},"max":{"x":3541,"y":388}},{"min":{"x":3614,"y":337},"max":{"x":3670,"y":391}},{"min":{"x":3742,"y":337},"max":{"x":3798,"y":391}},{"min":{"x":3871,"y":338},"max":{"x":3926,"y":391}},{"min":{"x":4000,"y":339},"max":{"x":4054,"y":391}},{"min":{"x":4129,"y":341},"max":{"x":4182,"y":391}},{"min":{"x":4258,"y":343},"max":{"x":4310,"y":392}},{"min":{"x":4387,"y":345},"max":{"x":4438,"y":393}},{"min":{"x":4515,"y":346},"max":{"x":4566,"y":393}},{"min":{"x":4644,"y":348},"max":{"x":4694,"y":393}},{"min":{"x":4772,"y":349},"max":{"x":4822,"y":392}},{"min":{"x":4900,"y":351},"max":{"x":4950,"y":391}},{"min":{"x":5026,"y":351},"max":{"x":5078,"y":391}},{"min":{"x":38,"y":445},"max":{"x":77,"y":508}},{"min":{"x":165,"y":445},"max":{"x":204,"y":508}},{"min":{"x":292,"y":445},"max":{"x":334,"y":508}},{"min":{"x":419,"y":442},"max":{"x":463,"y":508}},{"min":{"x":545,"y":440},"max":{"x":592,"y":508}},{"min":{"x":671,"y":441},"max":{"x":719,"y":508}},{"min":{"x":799,"y":441},"max":{"x":844,"y":507}},{"min":{"x":926,"y":431},"max":{"x":971,"y":507}},{"min":{"x":1054,"y":437},"max":{"x":1098,"y":507}},{"min":{"x":1175,"y":422},"max":{"x":1227,"y":507}},{"min":{"x":1300,"y":439},"max":{"x":1355,"y":507}},{"min":{"x":1432,"y":437},"max":{"x":1484,"y":507}},{"min":{"x":1564,"y":432},"max":{"x":1615,"y":507}},{"min":{"x":1694,"y":429},"max":{"x":1745,"y":507}},{"min":{"x":1821,"y":429},"max":{"x":1873,"y":507}},{"min":{"x":1947,"y":429},"max":{"x":2001,"y":507}},{"min":{"x":2076,"y":435},"max":{"x":2127,"y":508}},{"min":{"x":2205,"y":441},"max":{"x":2252,"y":508}},{"min":{"x":2336,"y":442},"max":{"x":2379,"y":508}},{"min":{"x":2468,"y":445},"max":{"x":2507,"y":508}},{"min":{"x":2594,"y":422},"max":{"x":2634,"y":482}},{"min":{"x":2724,"y":420},"max":{"x":2763,"y":482}},{"min":{"x":2853,"y":419},"max":{"x":2893,"y":482}},{"min":{"x":2983,"y":417},"max":{"x":3022,"y":482}},{"min":{"x":3111,"y":417},"max":{"x":3150,"y":483}},{"min":{"x":3237,"y":419},"max":{"x":3279,"y":484}},{"min":{"x":3364,"y":422},"max":{"x":3403,"y":484}},{"min":{"x":3490,"y":426},"max":{"x":3540,"y":484}},{"min":{"x":3617,"y":430},"max":{"x":3669,"y":487}},{"min":{"x":3747,"y":431},"max":{"x":3790,"y":487}},{"min":{"x":3877,"y":432},"max":{"x":3926,"y":488}},{"min":{"x":4007,"y":433},"max":{"x":4054,"y":489}},{"min":{"x":4137,"y":435},"max":{"x":4182,"y":490}},{"min":{"x":4267,"y":438},"max":{"x":4310,"y":490}},{"min":{"x":4394,"y":440},"max":{"x":4438,"y":490}},{"min":{"x":4520,"y":442},"max":{"x":4566,"y":490}},{"min":{"x":4646,"y":443},"max":{"x":4694,"y":490}},{"min":{"x":4773,"y":445},"max":{"x":4822,"y":490}},{"min":{"x":4899,"y":448},"max":{"x":4950,"y":489}},{"min":{"x":5025,"y":448},"max":{"x":5078,"y":490}},{"min":{"x":31,"y":574},"max":{"x":79,"y":638}},{"min":{"x":162,"y":574},"max":{"x":210,"y":638}},{"min":{"x":292,"y":574},"max":{"x":338,"y":638}},{"min":{"x":424,"y":572},"max":{"x":465,"y":638}},{"min":{"x":553,"y":573},"max":{"x":592,"y":638}},{"min":{"x":674,"y":575},"max":{"x":719,"y":638}},{"min":{"x":801,"y":569},"max":{"x":845,"y":638}},{"min":{"x":929,"y":557},"max":{"x":972,"y":638}},{"min":{"x":1067,"y":550},"max":{"x":1101,"y":638}},{"min":{"x":1195,"y":550},"max":{"x":1228,"y":638}},{"min":{"x":1324,"y":559},"max":{"x":1356,"y":638}},{"min":{"x":1452,"y":558},"max":{"x":1485,"y":638}},{"min":{"x":1579,"y":559},"max":{"x":1615,"y":638}},{"min":{"x":1707,"y":559},"max":{"x":1742,"y":638}},{"min":{"x":1835,"y":559},"max":{"x":1870,"y":638}},{"min":{"x":1964,"y":559},"max":{"x":1998,"y":638}},{"min":{"x":2091,"y":563},"max":{"x":2128,"y":638}},{"min":{"x":2219,"y":569},"max":{"x":2255,"y":638}},{"min":{"x":2341,"y":573},"max":{"x":2381,"y":638}},{"min":{"x":2464,"y":574},"max":{"x":2510,"y":638}},{"min":{"x":2587,"y":610},"max":{"x":2627,"y":672}},{"min":{"x":2717,"y":610},"max":{"x":2756,"y":672}},{"min":{"x":2849,"y":610},"max":{"x":2885,"y":673}},{"min":{"x":2978,"y":611},"max":{"x":3013,"y":673}},{"min":{"x":3106,"y":612},"max":{"x":3148,"y":673}},{"min":{"x":3233,"y":615},"max":{"x":3279,"y":674}},{"min":{"x":3361,"y":618},"max":{"x":3405,"y":673}},{"min":{"x":3490,"y":623},"max":{"x":3541,"y":676}},{"min":{"x":33,"y":704},"max":{"x":82,"y":768}},{"min":{"x":165,"y":704},"max":{"x":211,"y":768}},{"min":{"x":297,"y":704},"max":{"x":341,"y":768}},{"min":{"x":427,"y":705},"max":{"x":469,"y":768}},{"min":{"x":554,"y":705},"max":{"x":598,"y":768}},{"min":{"x":676,"y":701},"max":{"x":727,"y":768}},{"min":{"x":801,"y":695},"max":{"x":854,"y":769}},{"min":{"x":936,"y":683},"max":{"x":983,"y":769}},{"min":{"x":1064,"y":682},"max":{"x":1113,"y":769}},{"min":{"x":1192,"y":687},"max":{"x":1252,"y":769}},{"min":{"x":1320,"y":695},"max":{"x":1386,"y":769}},{"min":{"x":1447,"y":691},"max":{"x":1512,"y":769}},{"min":{"x":1575,"y":692},"max":{"x":1636,"y":769}},{"min":{"x":1703,"y":693},"max":{"x":1760,"y":769}},{"min":{"x":1831,"y":692},"max":{"x":1886,"y":769}},{"min":{"x":1959,"y":692},"max":{"x":2014,"y":769}},{"min":{"x":2088,"y":695},"max":{"x":2136,"y":769}},{"min":{"x":2217,"y":705},"max":{"x":2264,"y":768}},{"min":{"x":2346,"y":705},"max":{"x":2391,"y":768}},{"min":{"x":2470,"y":704},"max":{"x":2517,"y":768}},{"min":{"x":2589,"y":703},"max":{"x":2632,"y":765}},{"min":{"x":2717,"y":703},"max":{"x":2759,"y":765}},{"min":{"x":2845,"y":704},"max":{"x":2886,"y":766}},{"min":{"x":2974,"y":705},"max":{"x":3014,"y":766}},{"min":{"x":3105,"y":708},"max":{"x":3148,"y":766}},{"min":{"x":3238,"y":712},"max":{"x":3279,"y":766}},{"min":{"x":3366,"y":717},"max":{"x":3410,"y":766}},{"min":{"x":3495,"y":724},"max":{"x":3540,"y":770}},{"min":{"x":3625,"y":729},"max":{"x":3670,"y":772}},{"min":{"x":3753,"y":730},"max":{"x":3798,"y":772}},{"min":{"x":3882,"y":732},"max":{"x":3926,"y":772}},{"min":{"x":4011,"y":734},"max":{"x":4054,"y":772}},{"min":{"x":4139,"y":736},"max":{"x":4182,"y":772}},{"min":{"x":4267,"y":739},"max":{"x":4310,"y":772}},{"min":{"x":4394,"y":742},"max":{"x":4438,"y":772}},{"min":{"x":4521,"y":745},"max":{"x":4566,"y":772}},{"min":{"x":4648,"y":743},"max":{"x":4694,"y":774}},{"min":{"x":4775,"y":741},"max":{"x":4822,"y":777}},{"min":{"x":4901,"y":739},"max":{"x":4950,"y":780}},{"min":{"x":5027,"y":739},"max":{"x":5078,"y":780}},{"min":{"x":40,"y":834},"max":{"x":79,"y":897}},{"min":{"x":168,"y":834},"max":{"x":210,"y":897}},{"min":{"x":295,"y":834},"max":{"x":341,"y":898}},{"min":{"x":423,"y":835},"max":{"x":472,"y":898}},{"min":{"x":550,"y":835},"max":{"x":603,"y":898}},{"min":{"x":677,"y":835},"max":{"x":733,"y":898}},{"min":{"x":806,"y":821},"max":{"x":862,"y":898}},{"min":{"x":934,"y":812},"max":{"x":991,"y":898}},{"min":{"x":1062,"y":828},"max":{"x":1119,"y":898}},{"min":{"x":1189,"y":830},"max":{"x":1249,"y":898}},{"min":{"x":1317,"y":826},"max":{"x":1396,"y":898}},{"min":{"x":1445,"y":826},"max":{"x":1520,"y":898}},{"min":{"x":1573,"y":825},"max":{"x":1642,"y":898}},{"min":{"x":1699,"y":824},"max":{"x":1765,"y":898}},{"min":{"x":1827,"y":824},"max":{"x":1893,"y":898}},{"min":{"x":1956,"y":823},"max":{"x":2021,"y":898}},{"min":{"x":2086,"y":832},"max":{"x":2145,"y":898}},{"min":{"x":2214,"y":835},"max":{"x":2270,"y":898}},{"min":{"x":2342,"y":835},"max":{"x":2394,"y":898}},{"min":{"x":2471,"y":834},"max":{"x":2517,"y":898}},{"min":{"x":37,"y":964},"max":{"x":77,"y":1025}},{"min":{"x":166,"y":964},"max":{"x":206,"y":1025}},{"min":{"x":292,"y":964},"max":{"x":336,"y":1025}},{"min":{"x":418,"y":964},"max":{"x":466,"y":1025}},{"min":{"x":545,"y":964},"max":{"x":595,"y":1025}},{"min":{"x":674,"y":961},"max":{"x":724,"y":1025}},{"min":{"x":804,"y":952},"max":{"x":852,"y":1025}},{"min":{"x":933,"y":943},"max":{"x":980,"y":1025}},{"min":{"x":1062,"y":960},"max":{"x":1107,"y":1024}},{"min":{"x":1190,"y":962},"max":{"x":1235,"y":1024}},{"min":{"x":1318,"y":961},"max":{"x":1373,"y":1024}},{"min":{"x":1446,"y":959},"max":{"x":1498,"y":1024}},{"min":{"x":1570,"y":956},"max":{"x":1621,"y":1024}},{"min":{"x":1696,"y":954},"max":{"x":1747,"y":1024}},{"min":{"x":1824,"y":955},"max":{"x":1876,"y":1024}},{"min":{"x":1952,"y":954},"max":{"x":2005,"y":1025}},{"min":{"x":2082,"y":964},"max":{"x":2135,"y":1025}},{"min":{"x":2213,"y":964},"max":{"x":2262,"y":1025}},{"min":{"x":2340,"y":964},"max":{"x":2389,"y":1025}},{"min":{"x":2469,"y":964},"max":{"x":2513,"y":1025}},{"min":{"x":19,"y":1067},"max":{"x":72,"y":1130}},{"min":{"x":113,"y":1067},"max":{"x":168,"y":1130}},{"min":{"x":209,"y":1068},"max":{"x":264,"y":1130}},{"min":{"x":305,"y":1068},"max":{"x":360,"y":1130}},{"min":{"x":402,"y":1068},"max":{"x":455,"y":1130}},{"min":{"x":497,"y":1068},"max":{"x":552,"y":1130}},{"min":{"x":593,"y":1068},"max":{"x":648,"y":1130}},{"min":{"x":689,"y":1067},"max":{"x":744,"y":1130}},{"min":{"x":790,"y":1065},"max":{"x":829,"y":1128}},{"min":{"x":886,"y":1064},"max":{"x":925,"y":1128}},{"min":{"x":982,"y":1065},"max":{"x":1022,"y":1128}},{"min":{"x":1078,"y":1064},"max":{"x":1122,"y":1128}},{"min":{"x":1175,"y":1065},"max":{"x":1219,"y":1128}},{"min":{"x":1271,"y":1065},"max":{"x":1316,"y":1128}},{"min":{"x":1366,"y":1065},"max":{"x":1405,"y":1128}},{"min":{"x":1462,"y":1065},"max":{"x":1506,"y":1128}},{"min":{"x":1558,"y":1065},"max":{"x":1599,"y":1128}},{"min":{"x":1654,"y":1065},"max":{"x":1693,"y":1128}},{"min":{"x":1750,"y":1065},"max":{"x":1789,"y":1128}},{"min":{"x":1846,"y":1065},"max":{"x":1885,"y":1128}},{"min":{"x":1942,"y":1065},"max":{"x":1981,"y":1128}},{"min":{"x":2037,"y":1065},"max":{"x":2077,"y":1128}},{"min":{"x":2133,"y":1065},"max":{"x":2174,"y":1128}},{"min":{"x":2229,"y":1065},"max":{"x":2269,"y":1128}},{"min":{"x":2326,"y":1065},"max":{"x":2365,"y":1128}},{"min":{"x":2422,"y":1064},"max":{"x":2461,"y":1128}},{"min":{"x":2518,"y":1065},"max":{"x":2557,"y":1128}},{"min":{"x":2614,"y":1065},"max":{"x":2653,"y":1128}},{"min":{"x":2700,"y":1068},"max":{"x":2763,"y":1134}},{"min":{"x":2798,"y":1065},"max":{"x":2859,"y":1131}},{"min":{"x":2890,"y":1066},"max":{"x":2955,"y":1131}},{"min":{"x":2987,"y":1067},"max":{"x":3050,"y":1133}},{"min":{"x":3082,"y":1067},"max":{"x":3147,"y":1133}},{"min":{"x":3179,"y":1065},"max":{"x":3243,"y":1131}},{"min":{"x":3274,"y":1066},"max":{"x":3339,"y":1131}},{"min":{"x":3371,"y":1067},"max":{"x":3435,"y":1133}},{"min":{"x":3479,"y":1066},"max":{"x":3520,"y":1132}},{"min":{"x":3574,"y":1065},"max":{"x":3616,"y":1130}},{"min":{"x":3669,"y":1064},"max":{"x":3712,"y":1129}},{"min":{"x":3765,"y":1065},"max":{"x":3807,"y":1130}},{"min":{"x":3862,"y":1066},"max":{"x":3902,"y":1132}},{"min":{"x":3957,"y":1065},"max":{"x":3999,"y":1130}},{"min":{"x":4053,"y":1064},"max":{"x":4095,"y":1129}},{"min":{"x":4151,"y":1065},"max":{"x":4192,"y":1130}},{"min":{"x":4238,"y":1063},"max":{"x":4300,"y":1131}},{"min":{"x":4336,"y":1063},"max":{"x":4396,"y":1131}},{"min":{"x":4434,"y":1063},"max":{"x":4492,"y":1131}},{"min":{"x":4532,"y":1063},"max":{"x":4589,"y":1131}},{"min":{"x":4629,"y":1064},"max":{"x":4685,"y":1131}},{"min":{"x":4727,"y":1064},"max":{"x":4781,"y":1130}},{"min":{"x":4824,"y":1065},"max":{"x":4876,"y":1130}},{"min":{"x":4919,"y":1066},"max":{"x":4972,"y":1130}},{"min":{"x":10,"y":1163},"max":{"x":69,"y":1229}},{"min":{"x":109,"y":1163},"max":{"x":163,"y":1229}},{"min":{"x":203,"y":1164},"max":{"x":257,"y":1229}},{"min":{"x":300,"y":1164},"max":{"x":352,"y":1229}},{"min":{"x":395,"y":1164},"max":{"x":447,"y":1229}},{"min":{"x":492,"y":1164},"max":{"x":544,"y":1229}},{"min":{"x":587,"y":1164},"max":{"x":641,"y":1229}},{"min":{"x":685,"y":1163},"max":{"x":739,"y":1229}},{"min":{"x":792,"y":1161},"max":{"x":841,"y":1225}},{"min":{"x":888,"y":1162},"max":{"x":934,"y":1225}},{"min":{"x":983,"y":1162},"max":{"x":1026,"y":1225}},{"min":{"x":1078,"y":1162},"max":{"x":1117,"y":1225}},{"min":{"x":1174,"y":1162},"max":{"x":1212,"y":1225}},{"min":{"x":1270,"y":1162},"max":{"x":1308,"y":1225}},{"min":{"x":1366,"y":1162},"max":{"x":1404,"y":1225}},{"min":{"x":1462,"y":1162},"max":{"x":1501,"y":1225}},{"min":{"x":1559,"y":1162},"max":{"x":1600,"y":1225}},{"min":{"x":1656,"y":1162},"max":{"x":1700,"y":1225}},{"min":{"x":1752,"y":1162},"max":{"x":1799,"y":1225}},{"min":{"x":1849,"y":1161},"max":{"x":1897,"y":1225}},{"min":{"x":1942,"y":1161},"max":{"x":1995,"y":1225}},{"min":{"x":2036,"y":1161},"max":{"x":2092,"y":1225}},{"min":{"x":2133,"y":1161},"max":{"x":2188,"y":1225}},{"min":{"x":2228,"y":1161},"max":{"x":2284,"y":1225}},{"min":{"x":2325,"y":1161},"max":{"x":2380,"y":1225}},{"min":{"x":2422,"y":1161},"max":{"x":2475,"y":1225}},{"min":{"x":2520,"y":1161},"max":{"x":2571,"y":1225}},{"min":{"x":2617,"y":1161},"max":{"x":2666,"y":1225}},{"min":{"x":2696,"y":1164},"max":{"x":2754,"y":1230}},{"min":{"x":2799,"y":1162},"max":{"x":2849,"y":1227}},{"min":{"x":2897,"y":1162},"max":{"x":2944,"y":1226}},{"min":{"x":2986,"y":1164},"max":{"x":3039,"y":1227}},{"min":{"x":3088,"y":1163},"max":{"x":3135,"y":1227}},{"min":{"x":3185,"y":1162},"max":{"x":3232,"y":1227}},{"min":{"x":3281,"y":1162},"max":{"x":3328,"y":1227}},{"min":{"x":3377,"y":1164},"max":{"x":3425,"y":1229}},{"min":{"x":3481,"y":1163},"max":{"x":3535,"y":1227}},{"min":{"x":3577,"y":1161},"max":{"x":3628,"y":1226}},{"min":{"x":3673,"y":1161},"max":{"x":3720,"y":1224}},{"min":{"x":3767,"y":1162},"max":{"x":3814,"y":1225}},{"min":{"x":3861,"y":1162},"max":{"x":3908,"y":1226}},{"min":{"x":3958,"y":1161},"max":{"x":4004,"y":1225}},{"min":{"x":4057,"y":1161},"max":{"x":4103,"y":1224}},{"min":{"x":4152,"y":1162},"max":{"x":4203,"y":1226}},{"min":{"x":4246,"y":1162},"max":{"x":4299,"y":1229}},{"min":{"x":4341,"y":1162},"max":{"x":4395,"y":1229}},{"min":{"x":4436,"y":1161},"max":{"x":4490,"y":1229}},{"min":{"x":4531,"y":1161},"max":{"x":4586,"y":1229}},{"min":{"x":4626,"y":1161},"max":{"x":4682,"y":1229}},{"min":{"x":4723,"y":1161},"max":{"x":4778,"y":1229}},{"min":{"x":4816,"y":1162},"max":{"x":4873,"y":1229}},{"min":{"x":4911,"y":1162},"max":{"x":4969,"y":1229}},{"min":{"x":17,"y":1259},"max":{"x":57,"y":1324}},{"min":{"x":114,"y":1259},"max":{"x":152,"y":1324}},{"min":{"x":211,"y":1259},"max":{"x":248,"y":1324}},{"min":{"x":307,"y":1260},"max":{"x":345,"y":1324}},{"min":{"x":403,"y":1260},"max":{"x":441,"y":1324}},{"min":{"x":499,"y":1260},"max":{"x":537,"y":1324}},{"min":{"x":595,"y":1259},"max":{"x":632,"y":1324}},{"min":{"x":690,"y":1259},"max":{"x":728,"y":1324}},{"min":{"x":791,"y":1258},"max":{"x":846,"y":1322}},{"min":{"x":889,"y":1258},"max":{"x":942,"y":1322}},{"min":{"x":985,"y":1258},"max":{"x":1038,"y":1322}},{"min":{"x":1081,"y":1258},"max":{"x":1132,"y":1322}},{"min":{"x":1175,"y":1258},"max":{"x":1226,"y":1322}},{"min":{"x":1272,"y":1258},"max":{"x":1322,"y":1322}},{"min":{"x":1366,"y":1258},"max":{"x":1418,"y":1322}},{"min":{"x":1466,"y":1258},"max":{"x":1515,"y":1322}},{"min":{"x":1562,"y":1258},"max":{"x":1612,"y":1322}},{"min":{"x":1656,"y":1258},"max":{"x":1709,"y":1322}},{"min":{"x":1752,"y":1258},"max":{"x":1806,"y":1322}},{"min":{"x":1846,"y":1258},"max":{"x":1900,"y":1322}},{"min":{"x":1943,"y":1258},"max":{"x":1995,"y":1322}},{"min":{"x":2039,"y":1258},"max":{"x":2090,"y":1322}},{"min":{"x":2135,"y":1258},"max":{"x":2186,"y":1322}},{"min":{"x":2231,"y":1258},"max":{"x":2282,"y":1322}},{"min":{"x":2327,"y":1258},"max":{"x":2379,"y":1322}},{"min":{"x":2417,"y":1258},"max":{"x":2475,"y":1322}},{"min":{"x":2518,"y":1258},"max":{"x":2572,"y":1322}},{"min":{"x":2615,"y":1258},"max":{"x":2669,"y":1322}},{"min":{"x":2707,"y":1260},"max":{"x":2749,"y":1321}},{"min":{"x":2803,"y":1258},"max":{"x":2838,"y":1322}},{"min":{"x":2901,"y":1258},"max":{"x":2935,"y":1322}},{"min":{"x":2997,"y":1260},"max":{"x":3035,"y":1322}},{"min":{"x":3093,"y":1259},"max":{"x":3130,"y":1321}},{"min":{"x":3188,"y":1258},"max":{"x":3223,"y":1319}},{"min":{"x":3284,"y":1258},"max":{"x":3319,"y":1321}},{"min":{"x":3379,"y":1260},"max":{"x":3417,"y":1322}},{"min":{"x":3477,"y":1259},"max":{"x":3540,"y":1320}},{"min":{"x":3571,"y":1258},"max":{"x":3634,"y":1320}},{"min":{"x":3672,"y":1258},"max":{"x":3725,"y":1320}},{"min":{"x":3762,"y":1258},"max":{"x":3817,"y":1321}},{"min":{"x":3855,"y":1259},"max":{"x":3909,"y":1320}},{"min":{"x":3954,"y":1258},"max":{"x":4006,"y":1318}},{"min":{"x":4053,"y":1258},"max":{"x":4106,"y":1319}},{"min":{"x":4154,"y":1258},"max":{"x":4209,"y":1320}},{"min":{"x":4246,"y":1264},"max":{"x":4295,"y":1325}},{"min":{"x":4342,"y":1262},"max":{"x":4390,"y":1325}},{"min":{"x":4438,"y":1261},"max":{"x":4485,"y":1324}},{"min":{"x":4533,"y":1261},"max":{"x":4580,"y":1324}},{"min":{"x":4630,"y":1260},"max":{"x":4674,"y":1324}},{"min":{"x":4726,"y":1259},"max":{"x":4769,"y":1324}},{"min":{"x":4822,"y":1259},"max":{"x":4863,"y":1324}},{"min":{"x":4918,"y":1259},"max":{"x":4958,"y":1324}},{"min":{"x":22,"y":1355},"max":{"x":61,"y":1418}},{"min":{"x":118,"y":1355},"max":{"x":157,"y":1418}},{"min":{"x":214,"y":1356},"max":{"x":254,"y":1418}},{"min":{"x":310,"y":1356},"max":{"x":350,"y":1418}},{"min":{"x":406,"y":1356},"max":{"x":446,"y":1418}},{"min":{"x":502,"y":1356},"max":{"x":542,"y":1418}},{"min":{"x":598,"y":1356},"max":{"x":638,"y":1418}},{"min":{"x":694,"y":1355},"max":{"x":733,"y":1418}},{"min":{"x":785,"y":1355},"max":{"x":832,"y":1419}},{"min":{"x":878,"y":1355},"max":{"x":932,"y":1419}},{"min":{"x":978,"y":1355},"max":{"x":1032,"y":1419}},{"min":{"x":1080,"y":1355},"max":{"x":1131,"y":1419}},{"min":{"x":1174,"y":1355},"max":{"x":1228,"y":1420}},{"min":{"x":1270,"y":1355},"max":{"x":1324,"y":1420}},{"min":{"x":1365,"y":1355},"max":{"x":1419,"y":1420}},{"min":{"x":1462,"y":1355},"max":{"x":1515,"y":1420}},{"min":{"x":1559,"y":1355},"max":{"x":1609,"y":1419}},{"min":{"x":1651,"y":1355},"max":{"x":1702,"y":1419}},{"min":{"x":1749,"y":1355},"max":{"x":1794,"y":1419}},{"min":{"x":1839,"y":1355},"max":{"x":1886,"y":1419}},{"min":{"x":1937,"y":1355},"max":{"x":1980,"y":1419}},{"min":{"x":2034,"y":1355},"max":{"x":2076,"y":1419}},{"min":{"x":2131,"y":1355},"max":{"x":2172,"y":1419}},{"min":{"x":2227,"y":1355},"max":{"x":2268,"y":1419}},{"min":{"x":2322,"y":1355},"max":{"x":2364,"y":1419}},{"min":{"x":2417,"y":1355},"max":{"x":2460,"y":1419}},{"min":{"x":2515,"y":1355},"max":{"x":2557,"y":1419}},{"min":{"x":2610,"y":1355},"max":{"x":2655,"y":1419}},{"min":{"x":2704,"y":1357},"max":{"x":2746,"y":1419}},{"min":{"x":2797,"y":1354},"max":{"x":2842,"y":1417}},{"min":{"x":2892,"y":1355},"max":{"x":2939,"y":1419}},{"min":{"x":2988,"y":1356},"max":{"x":3035,"y":1421}},{"min":{"x":3084,"y":1356},"max":{"x":3131,"y":1419}},{"min":{"x":3180,"y":1354},"max":{"x":3227,"y":1416}},{"min":{"x":3277,"y":1355},"max":{"x":3322,"y":1416}},{"min":{"x":3374,"y":1356},"max":{"x":3418,"y":1419}},{"min":{"x":3474,"y":1356},"max":{"x":3526,"y":1420}},{"min":{"x":3572,"y":1354},"max":{"x":3620,"y":1418}},{"min":{"x":3665,"y":1354},"max":{"x":3714,"y":1417}},{"min":{"x":3755,"y":1355},"max":{"x":3807,"y":1420}},{"min":{"x":3853,"y":1355},"max":{"x":3904,"y":1421}},{"min":{"x":3956,"y":1354},"max":{"x":3999,"y":1419}},{"min":{"x":4045,"y":1354},"max":{"x":4097,"y":1417}},{"min":{"x":4143,"y":1355},"max":{"x":4195,"y":1418}},{"min":{"x":4247,"y":1359},"max":{"x":4297,"y":1419}},{"min":{"x":4344,"y":1359},"max":{"x":4391,"y":1419}},{"min":{"x":4440,"y":1359},"max":{"x":4486,"y":1419}},{"min":{"x":4537,"y":1359},"max":{"x":4581,"y":1419}},{"min":{"x":4633,"y":1358},"max":{"x":4676,"y":1418}},{"min":{"x":4730,"y":1357},"max":{"x":4771,"y":1418}},{"min":{"x":4827,"y":1356},"max":{"x":4866,"y":1418}},{"min":{"x":4922,"y":1355},"max":{"x":4962,"y":1418}},{"min":{"x":14,"y":1452},"max":{"x":63,"y":1517}},{"min":{"x":111,"y":1453},"max":{"x":160,"y":1517}},{"min":{"x":207,"y":1453},"max":{"x":256,"y":1517}},{"min":{"x":304,"y":1453},"max":{"x":352,"y":1517}},{"min":{"x":400,"y":1453},"max":{"x":448,"y":1516}},{"min":{"x":496,"y":1453},"max":{"x":544,"y":1517}},{"min":{"x":591,"y":1453},"max":{"x":640,"y":1517}},{"min":{"x":687,"y":1453},"max":{"x":736,"y":1517}},{"min":{"x":789,"y":1452},"max":{"x":829,"y":1515}},{"min":{"x":886,"y":1452},"max":{"x":925,"y":1515}},{"min":{"x":982,"y":1452},"max":{"x":1021,"y":1515}},{"min":{"x":1075,"y":1452},"max":{"x":1117,"y":1515}},{"min":{"x":1170,"y":1452},"max":{"x":1213,"y":1516}},{"min":{"x":1265,"y":1452},"max":{"x":1310,"y":1515}},{"min":{"x":1361,"y":1452},"max":{"x":1405,"y":1515}},{"min":{"x":1459,"y":1452},"max":{"x":1501,"y":1515}},{"min":{"x":1557,"y":1452},"max":{"x":1597,"y":1515}},{"min":{"x":1654,"y":1452},"max":{"x":1693,"y":1515}},{"min":{"x":1749,"y":1452},"max":{"x":1789,"y":1515}},{"min":{"x":1845,"y":1452},"max":{"x":1885,"y":1515}},{"min":{"x":1941,"y":1452},"max":{"x":1981,"y":1515}},{"min":{"x":2038,"y":1452},"max":{"x":2077,"y":1515}},{"min":{"x":2134,"y":1452},"max":{"x":2172,"y":1515}},{"min":{"x":2229,"y":1452},"max":{"x":2268,"y":1515}},{"min":{"x":2325,"y":1452},"max":{"x":2365,"y":1515}},{"min":{"x":2421,"y":1452},"max":{"x":2461,"y":1515}},{"min":{"x":2517,"y":1452},"max":{"x":2557,"y":1515}},{"min":{"x":2613,"y":1452},"max":{"x":2653,"y":1515}},{"min":{"x":2693,"y":1454},"max":{"x":2755,"y":1519}},{"min":{"x":2788,"y":1451},"max":{"x":2853,"y":1515}},{"min":{"x":2884,"y":1452},"max":{"x":2949,"y":1516}},{"min":{"x":2980,"y":1453},"max":{"x":3045,"y":1518}},{"min":{"x":3077,"y":1453},"max":{"x":3142,"y":1516}},{"min":{"x":3172,"y":1451},"max":{"x":3237,"y":1515}},{"min":{"x":3268,"y":1451},"max":{"x":3332,"y":1516}},{"min":{"x":3365,"y":1453},"max":{"x":3428,"y":1517}},{"min":{"x":3478,"y":1452},"max":{"x":3518,"y":1519}},{"min":{"x":3574,"y":1451},"max":{"x":3615,"y":1516}},{"min":{"x":3670,"y":1451},"max":{"x":3711,"y":1515}},{"min":{"x":3767,"y":1452},"max":{"x":3808,"y":1516}},{"min":{"x":3863,"y":1452},"max":{"x":3904,"y":1518}},{"min":{"x":3959,"y":1451},"max":{"x":4000,"y":1516}},{"min":{"x":4054,"y":1451},"max":{"x":4096,"y":1515}},{"min":{"x":4150,"y":1451},"max":{"x":4191,"y":1516}},{"min":{"x":4243,"y":1457},"max":{"x":4299,"y":1519}},{"min":{"x":4339,"y":1458},"max":{"x":4395,"y":1519}},{"min":{"x":4435,"y":1457},"max":{"x":4489,"y":1519}},{"min":{"x":4531,"y":1457},"max":{"x":4584,"y":1518}},{"min":{"x":4626,"y":1455},"max":{"x":4678,"y":1518}},{"min":{"x":4722,"y":1454},"max":{"x":4773,"y":1518}},{"min":{"x":4818,"y":1453},"max":{"x":4867,"y":1517}},{"min":{"x":4914,"y":1453},"max":{"x":4962,"y":1517}},{"min":{"x":17,"y":1550},"max":{"x":69,"y":1614}},{"min":{"x":116,"y":1550},"max":{"x":162,"y":1614}},{"min":{"x":214,"y":1551},"max":{"x":257,"y":1614}},{"min":{"x":311,"y":1551},"max":{"x":354,"y":1614}},{"min":{"x":408,"y":1551},"max":{"x":450,"y":1614}},{"min":{"x":503,"y":1551},"max":{"x":546,"y":1614}},{"min":{"x":598,"y":1551},"max":{"x":641,"y":1614}},{"min":{"x":692,"y":1550},"max":{"x":738,"y":1614}},{"min":{"x":782,"y":1549},"max":{"x":828,"y":1613}},{"min":{"x":881,"y":1549},"max":{"x":922,"y":1613}},{"min":{"x":981,"y":1549},"max":{"x":1019,"y":1613}},{"min":{"x":1077,"y":1549},"max":{"x":1116,"y":1612}},{"min":{"x":1173,"y":1549},"max":{"x":1212,"y":1612}},{"min":{"x":1269,"y":1549},"max":{"x":1308,"y":1612}},{"min":{"x":1365,"y":1549},"max":{"x":1404,"y":1612}},{"min":{"x":1461,"y":1549},"max":{"x":1500,"y":1612}},{"min":{"x":1557,"y":1549},"max":{"x":1595,"y":1612}},{"min":{"x":1652,"y":1549},"max":{"x":1690,"y":1613}},{"min":{"x":1745,"y":1549},"max":{"x":1786,"y":1613}},{"min":{"x":1838,"y":1549},"max":{"x":1885,"y":1613}},{"min":{"x":1933,"y":1549},"max":{"x":1983,"y":1613}},{"min":{"x":2028,"y":1549},"max":{"x":2081,"y":1613}},{"min":{"x":2123,"y":1549},"max":{"x":2177,"y":1613}},{"min":{"x":2219,"y":1549},"max":{"x":2272,"y":1613}},{"min":{"x":2316,"y":1549},"max":{"x":2368,"y":1613}},{"min":{"x":2412,"y":1549},"max":{"x":2463,"y":1613}},{"min":{"x":2509,"y":1549},"max":{"x":2558,"y":1613}},{"min":{"x":2606,"y":1549},"max":{"x":2653,"y":1613}},{"min":{"x":2701,"y":1551},"max":{"x":2759,"y":1615}},{"min":{"x":2798,"y":1549},"max":{"x":2855,"y":1612}},{"min":{"x":2898,"y":1549},"max":{"x":2952,"y":1612}},{"min":{"x":2992,"y":1551},"max":{"x":3048,"y":1612}},{"min":{"x":3089,"y":1550},"max":{"x":3144,"y":1612}},{"min":{"x":3182,"y":1548},"max":{"x":3240,"y":1611}},{"min":{"x":3278,"y":1549},"max":{"x":3336,"y":1612}},{"min":{"x":3374,"y":1550},"max":{"x":3432,"y":1614}},{"min":{"x":3466,"y":1549},"max":{"x":3520,"y":1615}},{"min":{"x":3565,"y":1548},"max":{"x":3616,"y":1613}},{"min":{"x":3666,"y":1548},"max":{"x":3710,"y":1612}},{"min":{"x":3764,"y":1549},"max":{"x":3810,"y":1612}},{"min":{"x":3863,"y":1549},"max":{"x":3910,"y":1613}},{"min":{"x":3958,"y":1548},"max":{"x":4003,"y":1612}},{"min":{"x":4053,"y":1548},"max":{"x":4093,"y":1612}},{"min":{"x":4143,"y":1548},"max":{"x":4190,"y":1613}},{"min":{"x":4244,"y":1556},"max":{"x":4289,"y":1616}},{"min":{"x":4341,"y":1555},"max":{"x":4386,"y":1616}},{"min":{"x":4437,"y":1554},"max":{"x":4482,"y":1616}},{"min":{"x":4533,"y":1552},"max":{"x":4578,"y":1616}},{"min":{"x":4628,"y":1552},"max":{"x":4674,"y":1615}},{"min":{"x":4725,"y":1551},"max":{"x":4771,"y":1615}},{"min":{"x":4821,"y":1550},"max":{"x":4868,"y":1615}},{"min":{"x":4917,"y":1550},"max":{"x":4966,"y":1614}},{"min":{"x":24,"y":1648},"max":{"x":63,"y":1711}},{"min":{"x":120,"y":1649},"max":{"x":160,"y":1712}},{"min":{"x":216,"y":1649},"max":{"x":256,"y":1712}},{"min":{"x":313,"y":1650},"max":{"x":352,"y":1712}},{"min":{"x":409,"y":1650},"max":{"x":449,"y":1712}},{"min":{"x":505,"y":1650},"max":{"x":544,"y":1712}},{"min":{"x":600,"y":1649},"max":{"x":640,"y":1712}},{"min":{"x":696,"y":1649},"max":{"x":736,"y":1712}},{"min":{"x":778,"y":1646},"max":{"x":840,"y":1711}},{"min":{"x":872,"y":1646},"max":{"x":935,"y":1711}},{"min":{"x":968,"y":1646},"max":{"x":1029,"y":1711}},{"min":{"x":1067,"y":1646},"max":{"x":1122,"y":1711}},{"min":{"x":1163,"y":1646},"max":{"x":1217,"y":1711}},{"min":{"x":1260,"y":1646},"max":{"x":1311,"y":1711}},{"min":{"x":1356,"y":1646},"max":{"x":1408,"y":1711}},{"min":{"x":1451,"y":1646},"max":{"x":1506,"y":1711}},{"min":{"x":1546,"y":1646},"max":{"x":1603,"y":1711}},{"min":{"x":1641,"y":1646},"max":{"x":1701,"y":1711}},{"min":{"x":1738,"y":1646},"max":{"x":1799,"y":1711}},{"min":{"x":1835,"y":1646},"max":{"x":1895,"y":1711}},{"min":{"x":1932,"y":1646},"max":{"x":1992,"y":1711}},{"min":{"x":2029,"y":1646},"max":{"x":2089,"y":1711}},{"min":{"x":2125,"y":1646},"max":{"x":2184,"y":1711}},{"min":{"x":2221,"y":1646},"max":{"x":2280,"y":1711}},{"min":{"x":2316,"y":1646},"max":{"x":2376,"y":1711}},{"min":{"x":2412,"y":1646},"max":{"x":2472,"y":1711}},{"min":{"x":2506,"y":1646},"max":{"x":2568,"y":1711}},{"min":{"x":2602,"y":1646},"max":{"x":2663,"y":1711}},{"min":{"x":2713,"y":1649},"max":{"x":2751,"y":1709}},{"min":{"x":2809,"y":1646},"max":{"x":2846,"y":1707}},{"min":{"x":2905,"y":1647},"max":{"x":2941,"y":1708}},{"min":{"x":3001,"y":1649},"max":{"x":3038,"y":1709}},{"min":{"x":3097,"y":1648},"max":{"x":3135,"y":1709}},{"min":{"x":3193,"y":1646},"max":{"x":3229,"y":1709}},{"min":{"x":3289,"y":1647},"max":{"x":3325,"y":1709}},{"min":{"x":3385,"y":1648},"max":{"x":3424,"y":1710}},{"min":{"x":3463,"y":1647},"max":{"x":3525,"y":1708}},{"min":{"x":3561,"y":1646},"max":{"x":3624,"y":1707}},{"min":{"x":3662,"y":1646},"max":{"x":3723,"y":1707}},{"min":{"x":3762,"y":1646},"max":{"x":3823,"y":1708}},{"min":{"x":3862,"y":1647},"max":{"x":3922,"y":1707}},{"min":{"x":3956,"y":1646},"max":{"x":4017,"y":1709}},{"min":{"x":4049,"y":1646},"max":{"x":4108,"y":1708}},{"min":{"x":4139,"y":1646},"max":{"x":4201,"y":1709}},{"min":{"x":4242,"y":1649},"max":{"x":4290,"y":1711}},{"min":{"x":4339,"y":1648},"max":{"x":4387,"y":1711}},{"min":{"x":4437,"y":1647},"max":{"x":4483,"y":1711}},{"min":{"x":4534,"y":1647},"max":{"x":4579,"y":1711}},{"min":{"x":4631,"y":1647},"max":{"x":4676,"y":1711}},{"min":{"x":4729,"y":1647},"max":{"x":4772,"y":1711}},{"min":{"x":4826,"y":1647},"max":{"x":4868,"y":1711}},{"min":{"x":4923,"y":1647},"max":{"x":4964,"y":1711}},{"min":{"x":21,"y":1746},"max":{"x":61,"y":1807}},{"min":{"x":118,"y":1746},"max":{"x":158,"y":1807}},{"min":{"x":213,"y":1747},"max":{"x":256,"y":1807}},{"min":{"x":310,"y":1747},"max":{"x":353,"y":1807}},{"min":{"x":406,"y":1747},"max":{"x":449,"y":1807}},{"min":{"x":502,"y":1747},"max":{"x":545,"y":1807}},{"min":{"x":597,"y":1747},"max":{"x":640,"y":1807}},{"min":{"x":694,"y":1746},"max":{"x":734,"y":1807}},{"min":{"x":789,"y":1743},"max":{"x":837,"y":1808}},{"min":{"x":882,"y":1743},"max":{"x":935,"y":1808}},{"min":{"x":974,"y":1743},"max":{"x":1033,"y":1808}},{"min":{"x":1067,"y":1743},"max":{"x":1130,"y":1808}},{"min":{"x":1162,"y":1743},"max":{"x":1226,"y":1808}},{"min":{"x":1258,"y":1743},"max":{"x":1321,"y":1808}},{"min":{"x":1354,"y":1743},"max":{"x":1418,"y":1808}},{"min":{"x":1452,"y":1743},"max":{"x":1514,"y":1808}},{"min":{"x":1549,"y":1743},"max":{"x":1610,"y":1808}},{"min":{"x":1648,"y":1743},"max":{"x":1704,"y":1808}},{"min":{"x":1748,"y":1743},"max":{"x":1794,"y":1808}},{"min":{"x":1847,"y":1744},"max":{"x":1887,"y":1808}},{"min":{"x":1943,"y":1744},"max":{"x":1984,"y":1808}},{"min":{"x":2038,"y":1744},"max":{"x":2082,"y":1808}},{"min":{"x":2134,"y":1744},"max":{"x":2177,"y":1808}},{"min":{"x":2230,"y":1744},"max":{"x":2274,"y":1808}},{"min":{"x":2326,"y":1743},"max":{"x":2370,"y":1808}},{"min":{"x":2423,"y":1743},"max":{"x":2464,"y":1808}},{"min":{"x":2519,"y":1743},"max":{"x":2560,"y":1808}},{"min":{"x":2614,"y":1743},"max":{"x":2661,"y":1808}},{"min":{"x":2710,"y":1746},"max":{"x":2754,"y":1809}},{"min":{"x":2804,"y":1744},"max":{"x":2851,"y":1806}},{"min":{"x":2900,"y":1744},"max":{"x":2948,"y":1808}},{"min":{"x":2997,"y":1746},"max":{"x":3045,"y":1811}},{"min":{"x":3092,"y":1746},"max":{"x":3140,"y":1811}},{"min":{"x":3188,"y":1744},"max":{"x":3236,"y":1809}},{"min":{"x":3284,"y":1744},"max":{"x":3331,"y":1806}},{"min":{"x":3382,"y":1746},"max":{"x":3427,"y":1807}},{"min":{"x":3476,"y":1744},"max":{"x":3520,"y":1808}},{"min":{"x":3573,"y":1743},"max":{"x":3619,"y":1807}},{"min":{"x":3672,"y":1743},"max":{"x":3717,"y":1805}},{"min":{"x":3769,"y":1744},"max":{"x":3812,"y":1808}},{"min":{"x":3865,"y":1745},"max":{"x":3910,"y":1809}},{"min":{"x":3961,"y":1743},"max":{"x":4006,"y":1809}},{"min":{"x":4057,"y":1743},"max":{"x":4104,"y":1806}},{"min":{"x":4150,"y":1744},"max":{"x":4195,"y":1807}},{"min":{"x":4244,"y":1742},"max":{"x":4293,"y":1806}},{"min":{"x":4341,"y":1742},"max":{"x":4389,"y":1806}},{"min":{"x":4438,"y":1742},"max":{"x":4485,"y":1806}},{"min":{"x":4535,"y":1742},"max":{"x":4580,"y":1806}},{"min":{"x":4631,"y":1743},"max":{"x":4676,"y":1806}},{"min":{"x":4728,"y":1743},"max":{"x":4770,"y":1806}},{"min":{"x":4824,"y":1744},"max":{"x":4866,"y":1806}},{"min":{"x":4921,"y":1745},"max":{"x":4962,"y":1807}},{"min":{"x":35,"y":1881},"max":{"x":88,"y":1944}},{"min":{"x":164,"y":1881},"max":{"x":211,"y":1944}},{"min":{"x":292,"y":1882},"max":{"x":341,"y":1944}},{"min":{"x":420,"y":1882},"max":{"x":473,"y":1944}},{"min":{"x":548,"y":1883},"max":{"x":600,"y":1944}},{"min":{"x":676,"y":1883},"max":{"x":722,"y":1944}},{"min":{"x":801,"y":1882},"max":{"x":847,"y":1944}},{"min":{"x":924,"y":1878},"max":{"x":977,"y":1944}},{"min":{"x":1049,"y":1871},"max":{"x":1107,"y":1944}},{"min":{"x":1175,"y":1866},"max":{"x":1236,"y":1944}},{"min":{"x":1304,"y":1865},"max":{"x":1364,"y":1944}},{"min":{"x":1443,"y":1881},"max":{"x":1494,"y":1944}},{"min":{"x":1572,"y":1881},"max":{"x":1626,"y":1944}},{"min":{"x":1701,"y":1881},"max":{"x":1754,"y":1944}},{"min":{"x":1829,"y":1882},"max":{"x":1882,"y":1944}},{"min":{"x":1957,"y":1882},"max":{"x":2010,"y":1944}},{"min":{"x":2078,"y":1882},"max":{"x":2137,"y":1944}},{"min":{"x":2201,"y":1882},"max":{"x":2273,"y":1948}},{"min":{"x":2326,"y":1882},"max":{"x":2403,"y":1948}},{"min":{"x":2453,"y":1882},"max":{"x":2531,"y":1948}},{"min":{"x":2581,"y":1874},"max":{"x":2657,"y":1948}},{"min":{"x":2711,"y":1876},"max":{"x":2784,"y":1946}},{"min":{"x":2839,"y":1870},"max":{"x":2911,"y":1944}},{"min":{"x":2980,"y":1881},"max":{"x":3031,"y":1944}},{"min":{"x":3108,"y":1881},"max":{"x":3163,"y":1944}},{"min":{"x":3227,"y":1869},"max":{"x":3296,"y":1944}},{"min":{"x":3345,"y":1858},"max":{"x":3433,"y":1944}},{"min":{"x":3469,"y":1856},"max":{"x":3565,"y":1944}},{"min":{"x":3595,"y":1854},"max":{"x":3696,"y":1944}},{"min":{"x":3721,"y":1852},"max":{"x":3825,"y":1944}},{"min":{"x":3849,"y":1847},"max":{"x":3954,"y":1944}},{"min":{"x":3979,"y":1848},"max":{"x":4081,"y":1944}},{"min":{"x":4108,"y":1850},"max":{"x":4202,"y":1944}},{"min":{"x":4238,"y":1855},"max":{"x":4325,"y":1944}},{"min":{"x":4374,"y":1863},"max":{"x":4445,"y":1944}},{"min":{"x":4514,"y":1876},"max":{"x":4568,"y":1944}},{"min":{"x":32,"y":2009},"max":{"x":85,"y":2074}},{"min":{"x":156,"y":2010},"max":{"x":214,"y":2075}},{"min":{"x":287,"y":2010},"max":{"x":343,"y":2075}},{"min":{"x":413,"y":2010},"max":{"x":473,"y":2075}},{"min":{"x":541,"y":2011},"max":{"x":596,"y":2075}},{"min":{"x":665,"y":2011},"max":{"x":732,"y":2075}},{"min":{"x":795,"y":2011},"max":{"x":859,"y":2075}},{"min":{"x":923,"y":2007},"max":{"x":986,"y":2075}},{"min":{"x":1049,"y":2000},"max":{"x":1114,"y":2075}},{"min":{"x":1175,"y":1995},"max":{"x":1243,"y":2075}},{"min":{"x":1304,"y":1994},"max":{"x":1372,"y":2075}},{"min":{"x":1436,"y":2009},"max":{"x":1498,"y":2074}},{"min":{"x":1573,"y":2009},"max":{"x":1622,"y":2075}},{"min":{"x":1697,"y":2009},"max":{"x":1751,"y":2075}},{"min":{"x":1821,"y":2010},"max":{"x":1881,"y":2075}},{"min":{"x":1949,"y":2010},"max":{"x":2010,"y":2075}},{"min":{"x":2077,"y":2010},"max":{"x":2140,"y":2075}},{"min":{"x":2201,"y":2011},"max":{"x":2273,"y":2077}},{"min":{"x":2325,"y":2011},"max":{"x":2403,"y":2077}},{"min":{"x":2453,"y":2011},"max":{"x":2531,"y":2077}},{"min":{"x":2581,"y":2003},"max":{"x":2657,"y":2077}},{"min":{"x":2711,"y":2005},"max":{"x":2784,"y":2077}},{"min":{"x":2838,"y":1999},"max":{"x":2911,"y":2075}},{"min":{"x":2973,"y":2009},"max":{"x":3035,"y":2075}},{"min":{"x":3102,"y":2009},"max":{"x":3159,"y":2074}},{"min":{"x":3227,"y":1998},"max":{"x":3296,"y":2075}},{"min":{"x":3346,"y":1987},"max":{"x":3433,"y":2075}},{"min":{"x":3468,"y":1985},"max":{"x":3565,"y":2075}},{"min":{"x":3595,"y":1984},"max":{"x":3696,"y":2075}},{"min":{"x":3721,"y":1977},"max":{"x":3824,"y":2075}},{"min":{"x":3849,"y":1976},"max":{"x":3954,"y":2075}},{"min":{"x":3979,"y":1977},"max":{"x":4081,"y":2075}},{"min":{"x":4108,"y":1979},"max":{"x":4202,"y":2075}},{"min":{"x":4238,"y":1984},"max":{"x":4325,"y":2075}},{"min":{"x":4374,"y":1992},"max":{"x":4446,"y":2075}},{"min":{"x":4511,"y":2005},"max":{"x":4572,"y":2075}},{"min":{"x":33,"y":2137},"max":{"x":72,"y":2202}},{"min":{"x":161,"y":2137},"max":{"x":200,"y":2202}},{"min":{"x":288,"y":2138},"max":{"x":328,"y":2202}},{"min":{"x":414,"y":2138},"max":{"x":457,"y":2202}},{"min":{"x":541,"y":2138},"max":{"x":588,"y":2202}},{"min":{"x":667,"y":2139},"max":{"x":724,"y":2202}},{"min":{"x":790,"y":2139},"max":{"x":858,"y":2202}},{"min":{"x":918,"y":2136},"max":{"x":982,"y":2202}},{"min":{"x":1045,"y":2129},"max":{"x":1115,"y":2202}},{"min":{"x":1174,"y":2124},"max":{"x":1242,"y":2202}},{"min":{"x":1304,"y":2123},"max":{"x":1365,"y":2202}},{"min":{"x":1436,"y":2137},"max":{"x":1485,"y":2202}},{"min":{"x":1570,"y":2137},"max":{"x":1609,"y":2202}},{"min":{"x":1698,"y":2137},"max":{"x":1737,"y":2202}},{"min":{"x":1824,"y":2138},"max":{"x":1865,"y":2202}},{"min":{"x":1951,"y":2138},"max":{"x":1994,"y":2202}},{"min":{"x":2078,"y":2138},"max":{"x":2125,"y":2202}},{"min":{"x":2201,"y":2138},"max":{"x":2273,"y":2206}},{"min":{"x":2326,"y":2139},"max":{"x":2403,"y":2206}},{"min":{"x":2453,"y":2139},"max":{"x":2531,"y":2206}},{"min":{"x":2581,"y":2132},"max":{"x":2657,"y":2206}},{"min":{"x":2711,"y":2134},"max":{"x":2784,"y":2206}},{"min":{"x":2839,"y":2128},"max":{"x":2911,"y":2202}},{"min":{"x":2974,"y":2137},"max":{"x":3022,"y":2202}},{"min":{"x":3107,"y":2137},"max":{"x":3146,"y":2202}},{"min":{"x":3227,"y":2127},"max":{"x":3295,"y":2202}},{"min":{"x":3345,"y":2116},"max":{"x":3433,"y":2202}},{"min":{"x":3469,"y":2114},"max":{"x":3565,"y":2202}},{"min":{"x":3595,"y":2113},"max":{"x":3696,"y":2202}},{"min":{"x":3722,"y":2110},"max":{"x":3824,"y":2202}},{"min":{"x":3849,"y":2105},"max":{"x":3954,"y":2202}},{"min":{"x":3980,"y":2106},"max":{"x":4080,"y":2202}},{"min":{"x":4108,"y":2108},"max":{"x":4202,"y":2202}},{"min":{"x":4238,"y":2113},"max":{"x":4326,"y":2202}},{"min":{"x":4374,"y":2121},"max":{"x":4444,"y":2202}},{"min":{"x":4511,"y":2134},"max":{"x":4567,"y":2202}},{"min":{"x":37,"y":2265},"max":{"x":77,"y":2331}},{"min":{"x":164,"y":2266},"max":{"x":204,"y":2331}},{"min":{"x":292,"y":2266},"max":{"x":332,"y":2330}},{"min":{"x":421,"y":2266},"max":{"x":459,"y":2330}},{"min":{"x":548,"y":2266},"max":{"x":587,"y":2330}},{"min":{"x":674,"y":2267},"max":{"x":716,"y":2329}},{"min":{"x":798,"y":2267},"max":{"x":847,"y":2329}},{"min":{"x":924,"y":2265},"max":{"x":977,"y":2329}},{"min":{"x":1049,"y":2258},"max":{"x":1107,"y":2329}},{"min":{"x":1175,"y":2253},"max":{"x":1236,"y":2328}},{"min":{"x":1304,"y":2252},"max":{"x":1364,"y":2328}},{"min":{"x":1446,"y":2265},"max":{"x":1484,"y":2328}},{"min":{"x":1575,"y":2265},"max":{"x":1614,"y":2328}},{"min":{"x":1702,"y":2265},"max":{"x":1741,"y":2328}},{"min":{"x":1830,"y":2266},"max":{"x":1869,"y":2328}},{"min":{"x":1958,"y":2266},"max":{"x":1996,"y":2328}},{"min":{"x":2086,"y":2266},"max":{"x":2124,"y":2330}},{"min":{"x":2201,"y":2266},"max":{"x":2273,"y":2335}},{"min":{"x":2327,"y":2266},"max":{"x":2403,"y":2335}},{"min":{"x":2453,"y":2266},"max":{"x":2531,"y":2335}},{"min":{"x":2582,"y":2261},"max":{"x":2657,"y":2335}},{"min":{"x":2711,"y":2263},"max":{"x":2784,"y":2332}},{"min":{"x":2840,"y":2257},"max":{"x":2911,"y":2330}},{"min":{"x":2983,"y":2265},"max":{"x":3020,"y":2328}},{"min":{"x":3111,"y":2265},"max":{"x":3151,"y":2328}},{"min":{"x":3228,"y":2256},"max":{"x":3296,"y":2328}},{"min":{"x":3347,"y":2245},"max":{"x":3433,"y":2328}},{"min":{"x":3470,"y":2243},"max":{"x":3565,"y":2328}},{"min":{"x":3596,"y":2242},"max":{"x":3695,"y":2328}},{"min":{"x":3723,"y":2239},"max":{"x":3824,"y":2328}},{"min":{"x":3850,"y":2234},"max":{"x":3953,"y":2329}},{"min":{"x":3981,"y":2235},"max":{"x":4081,"y":2328}},{"min":{"x":4109,"y":2237},"max":{"x":4202,"y":2328}},{"min":{"x":4239,"y":2242},"max":{"x":4326,"y":2328}},{"min":{"x":4374,"y":2250},"max":{"x":4444,"y":2328}},{"min":{"x":4514,"y":2263},"max":{"x":4567,"y":2328}},{"min":{"x":30,"y":2394},"max":{"x":79,"y":2460}},{"min":{"x":158,"y":2395},"max":{"x":205,"y":2460}},{"min":{"x":285,"y":2395},"max":{"x":333,"y":2459}},{"min":{"x":413,"y":2395},"max":{"x":462,"y":2459}},{"min":{"x":542,"y":2395},"max":{"x":590,"y":2459}},{"min":{"x":675,"y":2395},"max":{"x":717,"y":2458}},{"min":{"x":801,"y":2395},"max":{"x":847,"y":2458}},{"min":{"x":924,"y":2394},"max":{"x":977,"y":2458}},{"min":{"x":1049,"y":2387},"max":{"x":1107,"y":2458}},{"min":{"x":1175,"y":2382},"max":{"x":1236,"y":2458}},{"min":{"x":1304,"y":2381},"max":{"x":1364,"y":2458}},{"min":{"x":1440,"y":2394},"max":{"x":1486,"y":2458}},{"min":{"x":1568,"y":2394},"max":{"x":1616,"y":2458}},{"min":{"x":1695,"y":2394},"max":{"x":1742,"y":2459}},{"min":{"x":1823,"y":2395},"max":{"x":1870,"y":2459}},{"min":{"x":1951,"y":2395},"max":{"x":1999,"y":2459}},{"min":{"x":2078,"y":2395},"max":{"x":2128,"y":2459}},{"min":{"x":2201,"y":2395},"max":{"x":2273,"y":2464}},{"min":{"x":2327,"y":2395},"max":{"x":2403,"y":2464}},{"min":{"x":2453,"y":2395},"max":{"x":2531,"y":2464}},{"min":{"x":2582,"y":2390},"max":{"x":2657,"y":2464}},{"min":{"x":2711,"y":2392},"max":{"x":2784,"y":2462}},{"min":{"x":2840,"y":2386},"max":{"x":2911,"y":2459}},{"min":{"x":2978,"y":2394},"max":{"x":3023,"y":2458}},{"min":{"x":3105,"y":2394},"max":{"x":3153,"y":2458}},{"min":{"x":3227,"y":2385},"max":{"x":3296,"y":2459}},{"min":{"x":3347,"y":2374},"max":{"x":3433,"y":2459}},{"min":{"x":3469,"y":2372},"max":{"x":3565,"y":2458}},{"min":{"x":3596,"y":2371},"max":{"x":3696,"y":2458}},{"min":{"x":3722,"y":2364},"max":{"x":3825,"y":2459}},{"min":{"x":3850,"y":2363},"max":{"x":3953,"y":2459}},{"min":{"x":3980,"y":2364},"max":{"x":4081,"y":2458}},{"min":{"x":4108,"y":2366},"max":{"x":4202,"y":2458}},{"min":{"x":4238,"y":2371},"max":{"x":4326,"y":2458}},{"min":{"x":4374,"y":2378},"max":{"x":4445,"y":2458}},{"min":{"x":4514,"y":2392},"max":{"x":4567,"y":2459}},{"min":{"x":33,"y":2524},"max":{"x":80,"y":2589}},{"min":{"x":160,"y":2524},"max":{"x":208,"y":2589}},{"min":{"x":286,"y":2525},"max":{"x":336,"y":2588}},{"min":{"x":413,"y":2525},"max":{"x":466,"y":2588}},{"min":{"x":539,"y":2525},"max":{"x":596,"y":2588}},{"min":{"x":666,"y":2525},"max":{"x":727,"y":2588}},{"min":{"x":795,"y":2525},"max":{"x":854,"y":2589}},{"min":{"x":923,"y":2523},"max":{"x":981,"y":2589}},{"min":{"x":1049,"y":2516},"max":{"x":1109,"y":2589}},{"min":{"x":1175,"y":2511},"max":{"x":1238,"y":2588}},{"min":{"x":1304,"y":2510},"max":{"x":1366,"y":2588}},{"min":{"x":1436,"y":2524},"max":{"x":1490,"y":2588}},{"min":{"x":1570,"y":2524},"max":{"x":1622,"y":2588}},{"min":{"x":1697,"y":2524},"max":{"x":1750,"y":2588}},{"min":{"x":1823,"y":2525},"max":{"x":1878,"y":2588}},{"min":{"x":1950,"y":2525},"max":{"x":2006,"y":2588}},{"min":{"x":2076,"y":2525},"max":{"x":2133,"y":2588}},{"min":{"x":2201,"y":2525},"max":{"x":2273,"y":2593}},{"min":{"x":2326,"y":2525},"max":{"x":2403,"y":2593}},{"min":{"x":2453,"y":2524},"max":{"x":2531,"y":2593}},{"min":{"x":2582,"y":2519},"max":{"x":2657,"y":2593}},{"min":{"x":2711,"y":2521},"max":{"x":2784,"y":2593}},{"min":{"x":2839,"y":2515},"max":{"x":2911,"y":2588}},{"min":{"x":2973,"y":2524},"max":{"x":3028,"y":2588}},{"min":{"x":3107,"y":2524},"max":{"x":3154,"y":2588}},{"min":{"x":3227,"y":2513},"max":{"x":3295,"y":2588}},{"min":{"x":3348,"y":2503},"max":{"x":3433,"y":2588}},{"min":{"x":3469,"y":2501},"max":{"x":3565,"y":2588}},{"min":{"x":3596,"y":2500},"max":{"x":3695,"y":2588}},{"min":{"x":3722,"y":2497},"max":{"x":3828,"y":2588}},{"min":{"x":3849,"y":2492},"max":{"x":3955,"y":2589}},{"min":{"x":3980,"y":2493},"max":{"x":4080,"y":2589}},{"min":{"x":4107,"y":2495},"max":{"x":4202,"y":2589}},{"min":{"x":4238,"y":2500},"max":{"x":4325,"y":2588}},{"min":{"x":4374,"y":2507},"max":{"x":4445,"y":2588}},{"min":{"x":4510,"y":2521},"max":{"x":4567,"y":2588}},{"min":{"x":2606,"y":121},"max":{"x":2637,"y":184}},{"min":{"x":2732,"y":120},"max":{"x":2763,"y":183}},{"min":{"x":2857,"y":121},"max":{"x":2892,"y":181}},{"min":{"x":2983,"y":121},"max":{"x":3021,"y":181}},{"min":{"x":3109,"y":123},"max":{"x":3150,"y":181}},{"min":{"x":3236,"y":129},"max":{"x":3279,"y":181}},{"min":{"x":3365,"y":136},"max":{"x":3411,"y":182}},{"min":{"x":3492,"y":144},"max":{"x":3541,"y":188}},{"min":{"x":3622,"y":153},"max":{"x":3670,"y":189}},{"min":{"x":3748,"y":154},"max":{"x":3798,"y":190}},{"min":{"x":3874,"y":155},"max":{"x":3926,"y":191}},{"min":{"x":4002,"y":156},"max":{"x":4054,"y":191}},{"min":{"x":4129,"y":157},"max":{"x":4182,"y":191}},{"min":{"x":4257,"y":159},"max":{"x":4310,"y":190}},{"min":{"x":4385,"y":161},"max":{"x":4439,"y":190}},{"min":{"x":4512,"y":163},"max":{"x":4568,"y":190}},{"min":{"x":4640,"y":165},"max":{"x":4696,"y":191}},{"min":{"x":4768,"y":164},"max":{"x":4823,"y":193}},{"min":{"x":4896,"y":163},"max":{"x":4950,"y":194}},{"min":{"x":5024,"y":163},"max":{"x":5078,"y":194}},{"min":{"x":2589,"y":517},"max":{"x":2627,"y":578}},{"min":{"x":2719,"y":516},"max":{"x":2756,"y":578}},{"min":{"x":2848,"y":515},"max":{"x":2884,"y":579}},{"min":{"x":2978,"y":515},"max":{"x":3013,"y":579}},{"min":{"x":3108,"y":515},"max":{"x":3148,"y":580}},{"min":{"x":3238,"y":517},"max":{"x":3279,"y":580}},{"min":{"x":3368,"y":519},"max":{"x":3411,"y":579}},{"min":{"x":3497,"y":523},"max":{"x":3540,"y":581}},{"min":{"x":3627,"y":527},"max":{"x":3669,"y":583}},{"min":{"x":3753,"y":528},"max":{"x":3798,"y":584}},{"min":{"x":3879,"y":530},"max":{"x":3926,"y":584}},{"min":{"x":4005,"y":533},"max":{"x":4054,"y":585}},{"min":{"x":4131,"y":535},"max":{"x":4182,"y":585}},{"min":{"x":4257,"y":536},"max":{"x":4310,"y":585}},{"min":{"x":4383,"y":538},"max":{"x":4438,"y":584}},{"min":{"x":4511,"y":541},"max":{"x":4566,"y":583}},{"min":{"x":4638,"y":543},"max":{"x":4694,"y":582}},{"min":{"x":4767,"y":546},"max":{"x":4823,"y":581}},{"min":{"x":4895,"y":549},"max":{"x":4951,"y":580}},{"min":{"x":5023,"y":549},"max":{"x":5079,"y":582}},{"min":{"x":40,"y":2654},"max":{"x":79,"y":2718}},{"min":{"x":168,"y":2655},"max":{"x":207,"y":2718}},{"min":{"x":296,"y":2655},"max":{"x":337,"y":2717}},{"min":{"x":424,"y":2656},"max":{"x":461,"y":2717}},{"min":{"x":552,"y":2656},"max":{"x":596,"y":2717}},{"min":{"x":673,"y":2655},"max":{"x":726,"y":2717}},{"min":{"x":795,"y":2655},"max":{"x":858,"y":2717}},{"min":{"x":922,"y":2652},"max":{"x":986,"y":2717}},{"min":{"x":1049,"y":2645},"max":{"x":1114,"y":2717}},{"min":{"x":1175,"y":2640},"max":{"x":1242,"y":2717}},{"min":{"x":1304,"y":2639},"max":{"x":1367,"y":2717}},{"min":{"x":1448,"y":2654},"max":{"x":1487,"y":2717}},{"min":{"x":1577,"y":2654},"max":{"x":1616,"y":2717}},{"min":{"x":1705,"y":2655},"max":{"x":1745,"y":2717}},{"min":{"x":1833,"y":2655},"max":{"x":1874,"y":2717}},{"min":{"x":1961,"y":2655},"max":{"x":2004,"y":2717}},{"min":{"x":2077,"y":2655},"max":{"x":2133,"y":2717}},{"min":{"x":2201,"y":2655},"max":{"x":2273,"y":2722}},{"min":{"x":2326,"y":2655},"max":{"x":2403,"y":2722}},{"min":{"x":2453,"y":2655},"max":{"x":2531,"y":2722}},{"min":{"x":2582,"y":2648},"max":{"x":2657,"y":2722}},{"min":{"x":2711,"y":2650},"max":{"x":2784,"y":2722}},{"min":{"x":2839,"y":2644},"max":{"x":2911,"y":2718}},{"min":{"x":2985,"y":2654},"max":{"x":3026,"y":2718}},{"min":{"x":3114,"y":2654},"max":{"x":3153,"y":2717}},{"min":{"x":3227,"y":2643},"max":{"x":3295,"y":2717}},{"min":{"x":3347,"y":2632},"max":{"x":3434,"y":2717}},{"min":{"x":3469,"y":2630},"max":{"x":3565,"y":2717}},{"min":{"x":3596,"y":2629},"max":{"x":3696,"y":2717}},{"min":{"x":3722,"y":2626},"max":{"x":3824,"y":2717}},{"min":{"x":3849,"y":2621},"max":{"x":3954,"y":2717}},{"min":{"x":3980,"y":2622},"max":{"x":4080,"y":2717}},{"min":{"x":4108,"y":2624},"max":{"x":4202,"y":2718}},{"min":{"x":4238,"y":2629},"max":{"x":4326,"y":2717}},{"min":{"x":4374,"y":2637},"max":{"x":4445,"y":2717}},{"min":{"x":4513,"y":2650},"max":{"x":4566,"y":2717}},{"min":{"x":37,"y":2784},"max":{"x":77,"y":2847}},{"min":{"x":165,"y":2785},"max":{"x":205,"y":2847}},{"min":{"x":293,"y":2785},"max":{"x":333,"y":2846}},{"min":{"x":421,"y":2785},"max":{"x":461,"y":2846}},{"min":{"x":550,"y":2786},"max":{"x":589,"y":2846}},{"min":{"x":676,"y":2785},"max":{"x":718,"y":2845}},{"min":{"x":801,"y":2785},"max":{"x":851,"y":2845}},{"min":{"x":924,"y":2781},"max":{"x":980,"y":2845}},{"min":{"x":1049,"y":2774},"max":{"x":1109,"y":2845}},{"min":{"x":1175,"y":2769},"max":{"x":1236,"y":2846}},{"min":{"x":1304,"y":2768},"max":{"x":1364,"y":2845}},{"min":{"x":1445,"y":2784},"max":{"x":1485,"y":2845}},{"min":{"x":1574,"y":2784},"max":{"x":1614,"y":2845}},{"min":{"x":1702,"y":2784},"max":{"x":1742,"y":2845}},{"min":{"x":1831,"y":2785},"max":{"x":1870,"y":2845}},{"min":{"x":1959,"y":2785},"max":{"x":1998,"y":2845}},{"min":{"x":2087,"y":2785},"max":{"x":2126,"y":2846}},{"min":{"x":2201,"y":2785},"max":{"x":2273,"y":2851}},{"min":{"x":2327,"y":2785},"max":{"x":2403,"y":2851}},{"min":{"x":2453,"y":2785},"max":{"x":2531,"y":2851}},{"min":{"x":2582,"y":2777},"max":{"x":2657,"y":2851}},{"min":{"x":2711,"y":2779},"max":{"x":2784,"y":2851}},{"min":{"x":2840,"y":2773},"max":{"x":2911,"y":2846}},{"min":{"x":2982,"y":2784},"max":{"x":3022,"y":2845}},{"min":{"x":3111,"y":2784},"max":{"x":3151,"y":2845}},{"min":{"x":3227,"y":2772},"max":{"x":3296,"y":2845}},{"min":{"x":3347,"y":2761},"max":{"x":3433,"y":2845}},{"min":{"x":3469,"y":2759},"max":{"x":3565,"y":2845}},{"min":{"x":3596,"y":2758},"max":{"x":3695,"y":2845}},{"min":{"x":3722,"y":2755},"max":{"x":3825,"y":2845}},{"min":{"x":3850,"y":2750},"max":{"x":3953,"y":2845}},{"min":{"x":3979,"y":2751},"max":{"x":4081,"y":2845}},{"min":{"x":4108,"y":2753},"max":{"x":4202,"y":2846}},{"min":{"x":4238,"y":2758},"max":{"x":4326,"y":2846}},{"min":{"x":4374,"y":2766},"max":{"x":4444,"y":2845}},{"min":{"x":4513,"y":2779},"max":{"x":4567,"y":2845}},{"min":{"x":3615,"y":246},"max":{"x":3670,"y":291}},{"min":{"x":3742,"y":247},"max":{"x":3798,"y":290}},{"min":{"x":3869,"y":248},"max":{"x":3926,"y":290}},{"min":{"x":3996,"y":249},"max":{"x":4054,"y":289}},{"min":{"x":4124,"y":251},"max":{"x":4182,"y":289}},{"min":{"x":4252,"y":252},"max":{"x":4310,"y":290}},{"min":{"x":4380,"y":253},"max":{"x":4438,"y":290}},{"min":{"x":4507,"y":254},"max":{"x":4567,"y":290}},{"min":{"x":4635,"y":256},"max":{"x":4695,"y":289}},{"min":{"x":4764,"y":258},"max":{"x":4823,"y":288}},{"min":{"x":4893,"y":259},"max":{"x":4952,"y":288}},{"min":{"x":5021,"y":259},"max":{"x":5081,"y":288}},{"min":{"x":3621,"y":628},"max":{"x":3670,"y":679}},{"min":{"x":3749,"y":629},"max":{"x":3794,"y":679}},{"min":{"x":3877,"y":631},"max":{"x":3923,"y":678}},{"min":{"x":4005,"y":632},"max":{"x":4052,"y":678}},{"min":{"x":4131,"y":635},"max":{"x":4181,"y":677}},{"min":{"x":4257,"y":637},"max":{"x":4311,"y":676}},{"min":{"x":4384,"y":640},"max":{"x":4439,"y":675}},{"min":{"x":4511,"y":643},"max":{"x":4568,"y":675}},{"min":{"x":4638,"y":647},"max":{"x":4697,"y":675}},{"min":{"x":4766,"y":649},"max":{"x":4825,"y":675}},{"min":{"x":4894,"y":648},"max":{"x":4953,"y":677}},{"min":{"x":5022,"y":648},"max":{"x":5081,"y":677}}]}